[
    {
        "id": 1,
        "contenido": "Respuesta a la pregunta 1",
        "idtipoArchivo": 1,
        "fecha": "May 28, 2025, 08:00:00 AM",
        "idUsuario": 1
    },
    {
        "id": 2,
        "contenido": "Respuesta a la pregunta 2",
        "idtipoArchivo": 2,
        "fecha": "May 28, 2025, 08:05:00 AM",
        "idUsuario": 2
    },
    {
        "id": 3,
        "contenido": "Respuesta a la pregunta 3",
        "idtipoArchivo": 1,
        "fecha": "May 28, 2025, 08:10:00 AM",
        "idUsuario": 3
    },
    {
        "id": 4,
        "contenido": "Respuesta a la pregunta 4",
        "idtipoArchivo": 2,
        "fecha": "May 28, 2025, 08:15:00 AM",
        "idUsuario": 4
    },
    {
        "id": 5,
        "contenido": "Respuesta a la pregunta 5",
        "idtipoArchivo": 1,
        "fecha": "May 28, 2025, 08:20:00 AM",
        "idUsuario": 5
    },
    {
        "id": 6,
        "contenido": "Respuesta a la pregunta 6",
        "idtipoArchivo": 2,
        "fecha": "May 28, 2025, 08:25:00 AM",
        "idUsuario": 6
    },
    {
        "id": 7,
        "contenido": "Respuesta a la pregunta 7",
        "idtipoArchivo": 1,
        "fecha": "May 28, 2025, 08:30:00 AM",
        "idUsuario": 7
    },
    {
        "id": 8,
        "contenido": "Respuesta a la pregunta 8",
        "idtipoArchivo": 2,
        "fecha": "May 28, 2025, 08:35:00 AM",
        "idUsuario": 8
    }
]